zk_shell/__init__.py
zk_shell/acl.py
zk_shell/cli.py
zk_shell/copy_util.py
zk_shell/keys.py
zk_shell/pathmap.py
zk_shell/shell.py
zk_shell/statmap.py
zk_shell/tree.py
zk_shell/usage.py
zk_shell/util.py
zk_shell/watch_manager.py
zk_shell/watcher.py
zk_shell/xclient.py
zk_shell/tests/__init__.py
zk_shell/tests/shell_test_case.py
zk_shell/tests/test_acl_reader.py
zk_shell/tests/test_basic_cmds.py
zk_shell/tests/test_connect.py
zk_shell/tests/test_cp_cmds.py
zk_shell/tests/test_cp_urls.py
zk_shell/tests/test_four_letter_cmds.py
zk_shell/tests/test_json_cmds.py
zk_shell/tests/test_keys.py
zk_shell/tests/test_mirror_cmds.py
zk_shell/tests/test_util.py
zk_shell/tests/test_watcher.py
zk_shell-1.3.4.data/scripts/zk-shell
zk_shell-1.3.4.dist-info/LICENSE
zk_shell-1.3.4.dist-info/METADATA
zk_shell-1.3.4.dist-info/WHEEL
zk_shell-1.3.4.dist-info/top_level.txt
zk_shell-1.3.4.dist-info/RECORD
