Metadata-Version: 2.1
Name: zk-shell
Version: 1.3.4
Summary: A Python - Kazoo based - shell for ZooKeeper
Home-page: https://github.com/rgs1/zk_shell
Author: Raul Gutierrez Segales
Author-email: rgs@itevenworks.net
License: Apache
Keywords: ZooKeeper Kazoo shell
Platform: UNKNOWN
Classifier: Development Status :: 5 - Production/Stable
Classifier: License :: OSI Approved :: Apache Software License
Classifier: Programming Language :: Python
Classifier: Programming Language :: Python :: 2.7
Classifier: Programming Language :: Python :: 3.4
Classifier: Programming Language :: Python :: 3.5
Classifier: Programming Language :: Python :: 3.6
Classifier: Programming Language :: Python :: 3.7
Classifier: Topic :: System :: Distributed Computing
Classifier: Topic :: System :: Networking
Requires-Dist: ansicolors (>=1.1.8)
Requires-Dist: kazoo (>=2.6.1)
Requires-Dist: tabulate (>=0.8.3)
Requires-Dist: twitter.common.net (>=0.3.11)
Requires-Dist: xcmd (>=0.0.3)
Provides-Extra: test
Requires-Dist: ansicolors (>=1.1.8) ; extra == 'test'
Requires-Dist: kazoo (>=2.6.1) ; extra == 'test'
Requires-Dist: nose (>=1.3.7) ; extra == 'test'
Requires-Dist: tabulate (>=0.8.3) ; extra == 'test'
Requires-Dist: twitter.common.net (>=0.3.11) ; extra == 'test'
Requires-Dist: xcmd (>=0.0.3) ; extra == 'test'
